pyrinth/__init__.py
pyrinth/exceptions.py
pyrinth/literals.py
pyrinth/models.py
pyrinth/modrinth.py
pyrinth/projects.py
pyrinth/tags.py
pyrinth/teams.py
pyrinth/users.py
pyrinth/util.py
python_modrinth-1.2.1.dist-info/LICENSE
python_modrinth-1.2.1.dist-info/METADATA
python_modrinth-1.2.1.dist-info/WHEEL
python_modrinth-1.2.1.dist-info/top_level.txt
python_modrinth-1.2.1.dist-info/RECORD
