Metadata-Version: 2.1
Name: python-modrinth
Version: 1.2.1
Summary: A Python library that interacts with the Modrinth API
Home-page: https://github.com/RevolvingMadness/Pyrinth
Author: RevolvingMadness
Author-email: revolvingmad@gmail.com
Project-URL: Bug Tracker, https://github.com/RevolvingMadness/Pyrinth/issues
Classifier: Programming Language :: Python :: 3
Classifier: License :: OSI Approved :: MIT License
Classifier: Operating System :: OS Independent
Requires-Python: >=3.11
License-File: LICENSE
